drf_service_layer/__init__.py
drf_service_layer/services.py
drf_service_layer/views.py
drf_service_layer/viewsets.py
drf_service_layer-0.0.11.dist-info/LICENSE
drf_service_layer-0.0.11.dist-info/WHEEL
drf_service_layer-0.0.11.dist-info/METADATA
drf_service_layer-0.0.11.dist-info/RECORD
