Metadata-Version: 2.1
Name: drf-service-layer
Version: 0.0.11
Summary: Simple package which supports service-layered design for Django REST Framework.
Keywords: django,drf,service,layer,service-layer
Author-email: qu3vipon <qu3vipon@gmail.com>
Requires-Python: >=3.7
Classifier: Intended Audience :: Developers
Classifier: Operating System :: OS Independent
Classifier: Programming Language :: Python :: 3
Classifier: Programming Language :: Python :: 3.7
Classifier: Topic :: Internet
Classifier: Topic :: Software Development :: Libraries :: Python Modules
Classifier: Topic :: Software Development :: Libraries
Classifier: Topic :: Software Development
Classifier: Typing :: Typed
Classifier: Development Status :: 2 - Pre-Alpha
Classifier: Environment :: Web Environment
Classifier: License :: OSI Approved :: MIT License
Classifier: Topic :: Internet :: WWW/HTTP :: HTTP Servers
Classifier: Topic :: Internet :: WWW/HTTP
Requires-Dist: django
Requires-Dist: djangorestframework
Requires-Dist: pytest >=6.2.4,<7.0.0 ; extra == "dev"
Requires-Dist: pytest-django ==4.4.0 ; extra == "dev"
Requires-Dist: pytest-cov >=2.12.0,<3.0.0 ; extra == "dev"
Requires-Dist: flake8 >=3.8.3,<4.0.0 ; extra == "dev"
Requires-Dist: black ==20.8b1 ; extra == "dev"
Requires-Dist: isort >=5.0.6,<6.0.0 ; extra == "dev"
Project-URL: Documentation, https://github.com/qu3vipon/drf-service-layer
Project-URL: Source, https://github.com/qu3vipon/drf-service-layer
Provides-Extra: dev
